respy3/__init__.py
respy3/protocol.py
respy3-0.5.0.dist-info/WHEEL
respy3-0.5.0.dist-info/METADATA
respy3-0.5.0.dist-info/RECORD
