Metadata-Version: 2.1
Name: respy3
Version: 0.5.0
Summary: A RESP3 protocol parser for Python
License: BSD-3-Clause
Author: Harrison Morgan
Author-email: harrison.morgan@gmail.com
Requires-Python: >=3.7,<4.0
Classifier: License :: OSI Approved :: BSD License
Classifier: Programming Language :: Python :: 3
Classifier: Programming Language :: Python :: 3.7
Classifier: Programming Language :: Python :: 3.8
